{
  "total_authors": 762,
  "batches": [
    {
      "batch": 1,
      "file": "curated-links-001.json",
      "date": "2026-05-16",
      "range": "阿～爱（名字排序前48位）",
      "count": 48,
      "links": 99,
      "status": "done",
      "authors": [
        "阿尔波特·班杜拉", "阿尔伯特·艾利斯", "阿尔伯特·爱因斯坦",
        "阿尔伯特·班杜拉", "阿尔弗雷德-塔斯基", "阿尔弗雷德·阿德勒",
        "阿尔弗雷德·马汉", "阿克塞尔·霍耐特", "阿莉·拉塞尔·霍赫希尔德",
        "阿伦·贝克", "阿诺德·汤因比", "埃德加·沙因",
        "埃德蒙·葛斯", "埃德蒙·胡塞尔", "埃德温·威廉森",
        "埃蒂纳·温格", "埃弗里特·罗杰斯", "埃里克·埃里克森",
        "埃里克·方纳", "埃里克·坎德尔", "埃里克·雷蒙德",
        "埃里希·奧尔巴赫", "埃利奥特·尤里斯特", "埃莉诺·吉布森",
        "埃马纽埃尔·拉迪里", "埃米尔·涂尔干", "埃丝特·史坦伯格",
        "艾·里斯", "艾伯特-拉斯洛·巴拉巴西", "艾莉森·高普尼克",
        "艾伦·艾伯斯坦", "艾米莉·狄金森", "艾萨克·阿西莫夫",
        "艾萨克·牛顿", "爱德华·德西", "爱德华·霍夫曼"
      ]
    },
    {
      "batch": 2,
      "file": "curated-links-002.json",
      "date": "2026-05-17",
      "range": "Agneta Rahikainen～Richard Fardon（英文名前48位）",
      "count": 48,
      "links": 112,
      "status": "done",
      "authors": [
        "Agneta Rahikainen", "Agnieszka Gajewska", "Ananyo Bhattacharya",
        "Andrea Köhler-Ludescher", "Andreas D. Bold", "Andrius Gališanka",
        "Anita Burdman Feferman; Solomon Feferman", "Arthur Donovan; Knight, David",
        "Arturo Ezquerro", "Barry Katz", "Bart Schultz", "Betty Jean Craige",
        "Carlos Baker", "Catherine M. Rakow", "Christopher Zurn",
        "Claire Tomalin", "Cynthia L. Haven", "Dale Jacquette",
        "Daniel V. Papero", "Daniel W. Bjork", "David Bornstein",
        "Desmond MacHale", "Desmond Clarke", "Donald J. Albers",
        "Douglass Merrell", "Emile Gauvreau et al.", "Fay Fransella",
        "Francine Mary Netter", "Franz M. Wuketits", "Gemelli Giuliana",
        "Gerald L. Alexanderson; George Pólya", "Grifiths, A. B.; Wenley, R. M.",
        "James D. Watson", "John H. Flavell", "Joseph Brent",
        "Lawrence Principe", "Leopold Damrosch", "Makoto Ueda",
        "Manfred Vogt; Heinrich N. Dreesen; Peter Sundman; Ferdinand Wolf",
        "Marcel Fournier", "Margaret M. Caffrey", "Marjorie E. Weishaar",
        "Mary Catherine Bateson", "Matt Doeden", "Morton N. Cohen",
        "Nathan Houser", "Perez Zagorin", "Richard Fardon"
      ]
    }
  ],
  "summary": {
    "done": 96,
    "remaining": 666,
    "progress": "12.6%"
  }
}
